cnhkmcp/__init__.py
cnhkmcp/untracked/__init__.py
cnhkmcp/untracked/arXiv_API_Tool_Manual.md
cnhkmcp/untracked/arxiv_api.py
cnhkmcp/untracked/brain-consultant.md
cnhkmcp/untracked/forum_functions.py
cnhkmcp/untracked/platform_functions.py
cnhkmcp/untracked/sample_mcp_config.json
cnhkmcp/untracked/user_config.json
cnhkmcp/untracked/示例参考文档_BRAIN_Alpha_Test_Requirements_and_Tips.md
cnhkmcp/untracked/示例工作流_Alpha_explaination_workflow.md
cnhkmcp/untracked/示例工作流_BRAIN_6_Tips_Datafield_Exploration_Guide.md
cnhkmcp/untracked/示例工作流_BRAIN_Alpha_Improvement_Workflow.md
cnhkmcp/untracked/示例工作流_Dataset_Exploration_Expert_Manual.md
cnhkmcp/untracked/示例工作流_daily_report_workflow.md
cnhkmcp/untracked/配置前运行我_安装必要依赖包.py
cnhkmcp/untracked/AI打工人/BRAIN_AI打工人Mac_Linux版本.zip
cnhkmcp/untracked/AI打工人/双击安装AI打工人_Windows版本.exe
cnhkmcp/untracked/AI桌面插件/README.md
cnhkmcp/untracked/AI桌面插件/ace.log
cnhkmcp/untracked/AI桌面插件/config.json
cnhkmcp/untracked/AI桌面插件/icon.ico
cnhkmcp/untracked/AI桌面插件/icon.png
cnhkmcp/untracked/AI桌面插件/main.py
cnhkmcp/untracked/AI桌面插件/process_knowledge_base.py
cnhkmcp/untracked/AI桌面插件/rag_engine.py
cnhkmcp/untracked/AI桌面插件/requirements.txt
cnhkmcp/untracked/AI桌面插件/run.bat
cnhkmcp/untracked/AI桌面插件/首次运行打开我.py
cnhkmcp/untracked/AI桌面插件/get_knowledgeBase_tool/ace_lib.py
cnhkmcp/untracked/AI桌面插件/get_knowledgeBase_tool/fetch_all_datasets.py
cnhkmcp/untracked/AI桌面插件/get_knowledgeBase_tool/fetch_all_documentation.py
cnhkmcp/untracked/AI桌面插件/get_knowledgeBase_tool/fetch_all_operators.py
cnhkmcp/untracked/AI桌面插件/get_knowledgeBase_tool/helpful_functions.py
cnhkmcp/untracked/AI桌面插件/knowledge/001_10_Steps_to_Start_on_BRAIN_documentation.json
cnhkmcp/untracked/AI桌面插件/knowledge/001_Intermediate_Pack_-_Improve_your_Alpha_2_2_documentation.json
cnhkmcp/untracked/AI桌面插件/knowledge/001_Intermediate_Pack_-_Understand_Results_1_2_documentation.json
cnhkmcp/untracked/AI桌面插件/knowledge/001_Introduction_to_Alphas_documentation.json
cnhkmcp-2.3.5.dist-info/licenses/LICENSE
cnhkmcp-2.3.5.dist-info/METADATA
cnhkmcp-2.3.5.dist-info/WHEEL
cnhkmcp-2.3.5.dist-info/entry_points.txt
cnhkmcp-2.3.5.dist-info/top_level.txt
cnhkmcp-2.3.5.dist-info/RECORD
