Metadata-Version: 2.4
Name: cnhkmcp
Version: 2.3.5
Summary: A comprehensive Model Context Protocol (MCP) server for quantitative trading platform integration
Home-page: https://github.com/cnhk/cnhkmcp
Author: CNHK
Author-email: cnhk@example.com
Project-URL: Bug Reports, https://github.com/cnhk/cnhkmcp/issues
Project-URL: Source, https://github.com/cnhk/cnhkmcp
Project-URL: Documentation, https://github.com/cnhk/cnhkmcp#readme
Keywords: mcp,quantitative,trading,api,client
Classifier: Development Status :: 4 - Beta
Classifier: Intended Audience :: Developers
Classifier: Intended Audience :: Financial and Insurance Industry
Classifier: License :: OSI Approved :: MIT License
Classifier: Operating System :: OS Independent
Classifier: Programming Language :: Python :: 3
Classifier: Programming Language :: Python :: 3.8
Classifier: Programming Language :: Python :: 3.9
Classifier: Programming Language :: Python :: 3.10
Classifier: Programming Language :: Python :: 3.11
Classifier: Topic :: Office/Business :: Financial
Classifier: Topic :: Software Development :: Libraries :: Python Modules
Requires-Python: >=3.8
License-File: LICENSE
Requires-Dist: requests>=2.28.0
Requires-Dist: pandas>=1.5.0
Requires-Dist: selenium>=4.0.0
Requires-Dist: beautifulsoup4>=4.11.0
Requires-Dist: mcp>=0.1.0
Requires-Dist: pydantic>=1.10.0
Requires-Dist: lxml>=4.9.0
Provides-Extra: dev
Requires-Dist: pytest>=6.0; extra == "dev"
Requires-Dist: pytest-asyncio>=0.18.0; extra == "dev"
Requires-Dist: black>=21.0; extra == "dev"
Requires-Dist: flake8>=3.8; extra == "dev"
Dynamic: author
Dynamic: author-email
Dynamic: classifier
Dynamic: description
Dynamic: description-content-type
Dynamic: home-page
Dynamic: keywords
Dynamic: license-file
Dynamic: project-url
Dynamic: provides-extra
Dynamic: requires-dist
Dynamic: requires-python
Dynamic: summary
